Metadata-Version: 1.2
Name: inheritance-graph
Version: 0.4
Summary: A tool to help debug inheritance failures.
Home-page: https://github.com/NeilGirdhar/inheritance_graph
Author: Neil Girdhar
Author-email: mistersheik@gmail.com
License: UNKNOWN
Download-URL: https://github.com/neilgirdhar/inheritance_graph/archive/0.4.tar.gz
Keywords: inheritance,debugging
Platform: UNKNOWN
Classifier: Development Status :: 5 - Production/Stable
Classifier: Intended Audience :: Developers
Classifier: License :: OSI Approved :: MIT License
Classifier: Operating System :: OS Independent
Classifier: Programming Language :: Python
Classifier: Programming Language :: Python :: 3
Classifier: Programming Language :: Python :: 3.4
Classifier: Programming Language :: Python :: 3.5
Classifier: Programming Language :: Python :: 3.6
Requires-Python: >=3.4
